{
  "assessmentName": "Dev Rection",
  "assessment_id": "28u3qinsgp",
  "nik_participant": "JIM01",
  "memo": "",
  "course_id": "c2lg1bhjv0",
  "answers": [
    {
      "question_id": "hpgrqztnxb",
      "answer": "jawagan2",
      "note": ""
    },
    {
      "question_id": "onjykb3lt6",
      "answer": "ok gas",
      "note": ""
    },
    {
      "question_id": "z3c9ql5aoa",
      "answer": "vveyuspsmu",
      "note": "noted"
    },
    {
      "question_id": "e3gqwbh5hy",
      "answer": "vgi8pjnxcz",
      "note": ""
    }
  ]
}